edc_lab_dashboard/__init__.py
edc_lab_dashboard/apps.py
edc_lab_dashboard/auth_objects.py
edc_lab_dashboard/auths.py
edc_lab_dashboard/dashboard_templates.py
edc_lab_dashboard/dashboard_urls.py
edc_lab_dashboard/middleware.py
edc_lab_dashboard/models.py
edc_lab_dashboard/navbars.py
edc_lab_dashboard/urls.py
edc_lab_dashboard/wsgi.py
edc_lab_dashboard/migrations/0001_initial.py
edc_lab_dashboard/migrations/0002_alter_edcpermissions_device_created_and_more.py
edc_lab_dashboard/migrations/0003_edcpermissions_locale_created_and_more.py
edc_lab_dashboard/migrations/__init__.py
edc_lab_dashboard/model_wrappers/__init__.py
edc_lab_dashboard/model_wrappers/aliquot_model_wrapper.py
edc_lab_dashboard/model_wrappers/base_box_item_model_wrapper.py
edc_lab_dashboard/model_wrappers/box_model_wrapper.py
edc_lab_dashboard/model_wrappers/manage_box_item_model_wrapper.py
edc_lab_dashboard/model_wrappers/manifest_item_model_wrapper.py
edc_lab_dashboard/model_wrappers/manifest_model_wrapper.py
edc_lab_dashboard/model_wrappers/requisition_model_wrapper.py
edc_lab_dashboard/model_wrappers/result_model_wrapper.py
edc_lab_dashboard/model_wrappers/verify_box_model_wrapper.py
edc_lab_dashboard/static/edc_lab_dashboard/beep-03.mp3
edc_lab_dashboard/static/edc_lab_dashboard/css/extra.css
edc_lab_dashboard/static/edc_lab_dashboard/css/print.css
edc_lab_dashboard/static/edc_lab_dashboard/images/checked.png
edc_lab_dashboard/static/edc_lab_dashboard/images/unchecked.png
edc_lab_dashboard/static/edc_lab_dashboard/js/beep.js
edc_lab_dashboard/templates/edc_lab_dashboard/action_listboard.html
edc_lab_dashboard/templates/edc_lab_dashboard/aliquot_listboard.html
edc_lab_dashboard/templates/edc_lab_dashboard/base.html
edc_lab_dashboard/templates/edc_lab_dashboard/base_listboard.html
edc_lab_dashboard/templates/edc_lab_dashboard/box_listboard.html
edc_lab_dashboard/templates/edc_lab_dashboard/home.html
edc_lab_dashboard/templates/edc_lab_dashboard/listboard.html
edc_lab_dashboard-1.0.2.dist-info/licenses/AUTHORS.rst
edc_lab_dashboard-1.0.2.dist-info/licenses/LICENSE
edc_lab_dashboard-1.0.2.dist-info/METADATA
edc_lab_dashboard-1.0.2.dist-info/WHEEL
edc_lab_dashboard-1.0.2.dist-info/top_level.txt
edc_lab_dashboard-1.0.2.dist-info/RECORD
